nnn/__init__.py
nnn/base_ranker.py
nnn/base_retriever.py
nnn/dn_ranker.py
nnn/faiss_cpu_retriever.py
nnn/faiss_gpu_retriever.py
nnn/nnn_ranker.py
nnn/nnn_retriever.py
nnn/ranker.py
nnn/retriever.py
nnn_retrieval-1.0.1.dist-info/LICENSE
nnn_retrieval-1.0.1.dist-info/METADATA
nnn_retrieval-1.0.1.dist-info/WHEEL
nnn_retrieval-1.0.1.dist-info/top_level.txt
nnn_retrieval-1.0.1.dist-info/RECORD
