Metadata-Version: 2.1
Name: nnn-retrieval
Version: 1.0.1
Summary: Simple and efficient training-free methods for correcting errors in contrastive image-text retrieval!
Author: Neil Chowdhury, Sumedh Shenoy, Franklin Wang
License: MIT License
Project-URL: Homepage, https://multimodal-interpretability.csail.mit.edu/nnn/
Classifier: Intended Audience :: Developers
Classifier: Intended Audience :: Education
Classifier: Intended Audience :: Science/Research
Classifier: License :: OSI Approved :: MIT License
Classifier: Operating System :: OS Independent
Classifier: Programming Language :: Python :: 3
Classifier: Topic :: Scientific/Engineering :: Artificial Intelligence
Requires-Python: >=3.6
License-File: LICENSE
Requires-Dist: torch
Requires-Dist: tqdm
Requires-Dist: numpy
Provides-Extra: dev
Requires-Dist: pytest ; extra == 'dev'
Requires-Dist: pre-commit ; extra == 'dev'
Provides-Extra: faiss_cpu
Requires-Dist: faiss-cpu ; extra == 'faiss_cpu'
Provides-Extra: faiss_gpu
Requires-Dist: faiss-gpu ; extra == 'faiss_gpu'
